MANIFEST.in
README.md
opencv_cflags_libs.py
setup.py
utils.py
whycon-code.jpg
./Makefile
./VERSION.txt
./utils.py
./src/CWhyconWrapper.cpp
./src/CWhyconWrapper.h
./src/pywhycon.cpp
./whycon_core/Makefile
./whycon_core/README.md
./whycon_core/src/CCircleDetect.cpp
./whycon_core/src/CCircleDetect.h
./whycon_core/src/CNecklace.cpp
./whycon_core/src/CNecklace.h
./whycon_core/src/CRawImage.cpp
./whycon_core/src/CRawImage.h
./whycon_core/src/CTimer.cpp
./whycon_core/src/CTimer.h
./whycon_core/src/CTransformation.cpp
./whycon_core/src/CTransformation.h
./whycon_core/src/CWhycon.cpp
./whycon_core/src/CWhycon.h
./whycon_core/src/SStructDefs.h
./whycon_core/src/whycon.h
config/camera_calibration.example.yml
config/space_calibration.autocalibration_result.yml
config/space_calibration.example.yml
whycon.egg-info/PKG-INFO
whycon.egg-info/SOURCES.txt
whycon.egg-info/dependency_links.txt
whycon.egg-info/requires.txt
whycon.egg-info/top_level.txt