Metadata-Version: 2.1
Name: whycon
Version: 1.0.1
Summary: Python wrapper for Whycon (Whycode),  precise, efficient and low-cost localization system
Home-page: https://github.com/ivomarvan/pywhycon
Author: Ivo Marvan
Author-email: ivo@marvan.cz
License: MIT
Keywords: localization,whycode,whycon
Platform: UNKNOWN
Classifier: Development Status :: 3 - Alpha
Classifier: License :: OSI Approved :: MIT License
Classifier: Programming Language :: Python :: 3
